matplotlib_venn/__init__.py
matplotlib_venn/_arc.py
matplotlib_venn/_common.py
matplotlib_venn/_math.py
matplotlib_venn/_region.py
matplotlib_venn/_util.py
matplotlib_venn/_venn2.py
matplotlib_venn/_venn3.py
matplotlib_venn/layout/venn2/__init__.py
matplotlib_venn/layout/venn2/exact.py
matplotlib_venn/layout/venn3/__init__.py
matplotlib_venn/layout/venn3/pairwise.py
matplotlib_venn-1.0.0a0.dist-info/LICENSE
matplotlib_venn-1.0.0a0.dist-info/METADATA
matplotlib_venn-1.0.0a0.dist-info/WHEEL
matplotlib_venn-1.0.0a0.dist-info/top_level.txt
matplotlib_venn-1.0.0a0.dist-info/zip-safe
matplotlib_venn-1.0.0a0.dist-info/RECORD
