Metadata-Version: 2.1
Name: matplotlib-venn
Version: 1.0.0a0
Summary: Functions for plotting area-proportional two- and three-way Venn diagrams in matplotlib.
Home-page: https://github.com/konstantint/matplotlib-venn
Author: Konstantin Tretyakov
Author-email: kt@umn.ee
License: MIT
Keywords: matplotlib plotting charts venn-diagrams
Platform: Platform Independent
Classifier: Development Status :: 5 - Production/Stable
Classifier: Intended Audience :: Science/Research
Classifier: License :: OSI Approved :: MIT License
Classifier: Operating System :: OS Independent
Classifier: Programming Language :: Python :: 3
Classifier: Topic :: Scientific/Engineering :: Visualization
License-File: LICENSE
Requires-Dist: matplotlib
Requires-Dist: numpy
Requires-Dist: scipy
